<OBRICO>
	<CLIENTES>
		<CLIENTE>
			<NIF>11111111A</NIF>
			<NOMBRE>ANTONIO GOMEZ PEREZ</NOMBRE>
			<DIRECCION>CUENCA 244</DIRECCION>
			<TELEFONO>666589541</TELEFONO>
		</CLIENTE>	
		<CLIENTE>
			<NIF>22222222B</NIF>
			<NOMBRE>JUANA DELGADO DIAZ</NOMBRE>
			<DIRECCION>CANONIGO 7</DIRECCION>
			<TELEFONO>954722301</TELEFONO>
		</CLIENTE>	
		<CLIENTE>
			<NIF>44444444Y</NIF>
			<NOMBRE>PEDRO VERDUGO MENA</NOMBRE>
			<DIRECCION>AVILA 5</DIRECCION>
			<TELEFONO>625412532</TELEFONO>
		</CLIENTE>	
	</CLIENTES>
	
	<OPERARIOS>
		<OPERARIO>
			<NIF>55555555T</NIF>
			<NOMBRE>MARCOS HARO MAR</NOMBRE>
		</OPERARIO>
		<OPERARIO>
			<NIF>66666666G</NIF>
			<NOMBRE>GONZALO NAZARENO DIAZ</NOMBRE>
		</OPERARIO>
		
	</OPERARIOS>

	<ADMINISTRATIVOS>
		<ADMINISTRATIVO>
			<NIF>77777777R</NIF>
			<NOMBRE>SOL VERA LUQUE</NOMBRE>
		</ADMINISTRATIVO>
		<ADMINISTRATIVO>
			<NIF>88888888O</NIF>
			<NOMBRE>ERNESTO SEVILLA LOZA</NOMBRE>
		</ADMINISTRATIVO>
	</ADMINISTRATIVOS>

	<MATERIALES>
		<MATERIAL>
			<CODIGO>FON001</CODIGO>
			<NOMBRE>DESATASCADOR</NOMBRE>
			<PRECIO>10.25</PRECIO>
			<DESCRIPCION>ACIDO CLORHIDRICO PARA DESATASCAR TUBERIAS</DESCRIPCION>
		</MATERIAL>
		<MATERIAL>
			<CODIGO>FON002</CODIGO>
			<NOMBRE>GUIA</NOMBRE>
			<PRECIO>17.50</PRECIO>
			<DESCRIPCION>GUIA PARA DESATASCAR</DESCRIPCION>
		</MATERIAL>
		<MATERIAL>
			<CODIGO>ALB001</CODIGO>
			<NOMBRE>CEMENTO COLA</NOMBRE>
			<PRECIO>84.50</PRECIO>
			<DESCRIPCION>CEMENTO COLA PARA HUMEDADES</DESCRIPCION>
		</MATERIAL>
		<MATERIAL>
			<CODIGO>ALB002</CODIGO>
			<NOMBRE>LIJA</NOMBRE>
			<PRECIO>5.45</PRECIO>
			<DESCRIPCION>LIJA DE AGUA DE 400</DESCRIPCION>
		</MATERIAL>
	</MATERIALES>

	<CITAS>
		<CITA>
		<ID>1</ID>
		<FECHA>17-01-2018</FECHA>
		<CLIENTE>22222222b</CLIENTE>
		<DESCRIPCION>FREGADERO ATASCADO</DESCRIPCION>
		<MATERIALES>
			<MATERIAL>FON001</MATERIAL>
			<MATERIAL>FON002</MATERIAL>
		</MATERIALES>
		<ADMINISTRATIVO>77777777R</ADMINISTRATIVO>
		<OPERARIOS>
			<OPERARIO>66666666G</OPERARIO>
		</OPERARIOS>
		<INCIDENCIAS>
			<INCIDENCIA>
				<NUMERO>1</NUMERO>
				<DESCRIPCION>NO ESTA EL CLIENTE</DESCRIPCION>
			</INCIDENCIA>
			<INCIDENCIA>
				<NUMERO></NUMERO>
				<DESCRIPCION></DESCRIPCION>
			</INCIDENCIA>
		</INCIDENCIAS>
	</CITA>
	<CITA>
		<ID>1</ID>
		<FECHA>17-01-2018</FECHA>
		<CLIENTE>22222222B</CLIENTE>
		<DESCRIPCION>FREGADERO ATASCADO</DESCRIPCION>
		<MATERIALES>
			<MATERIAL>FON001</MATERIAL>
			<MATERIAL>FON002</MATERIAL>
		</MATERIALES>
		<ADMINISTRATIVO>77777777R</ADMINISTRATIVO>
		<OPERARIOS>
			<OPERARIO>66666666G</OPERARIO>
		</OPERARIOS>
		<INCIDENCIAS>
			<INCIDENCIA>
				<NUMERO>1</NUMERO>
				<DESCRIPCION>NO ESTA EL CLIENTE</DESCRIPCION>
			</INCIDENCIA>
			<INCIDENCIA>
				<NUMERO></NUMERO>
				<DESCRIPCION></DESCRIPCION>
			</INCIDENCIA>
		</INCIDENCIAS>
	</CITA>
	<CITA>
		<ID>2</ID>
		<FECHA>17-02-2018</FECHA>
		<CLIENTE>11111111A</CLIENTE>
		<DESCRIPCION>GOTERAS TEJADO</DESCRIPCION>
		<MATERIALES>
			<MATERIAL>ALB001</MATERIAL>
			<MATERIAL>ALB002</MATERIAL>
		</MATERIALES>
		<ADMINISTRATIVO>77777777R</ADMINISTRATIVO>
		<OPERARIOS>
			<OPERARIO>55555555T</OPERARIO>
			<OPERARIO>99999999N</OPERARIO>
		</OPERARIOS>
		<INCIDENCIAS>
			<INCIDENCIA>
				<NUMERO>1</NUMERO>
				<DESCRIPCION>NO ACCESO AL TEJADO</DESCRIPCION>
			</INCIDENCIA>
			<INCIDENCIA>
				<NUMERO>2</NUMERO>
				<DESCRIPCION>HUMEDAD DESDE EL VECINO</DESCRIPCION>
			</INCIDENCIA>
		</INCIDENCIAS>
	</CITA>
		<CITA>
		<ID>3</ID>
		<FECHA>22-12-2017</FECHA>
		<CLIENTE>44444444Y</CLIENTE>
		<DESCRIPCION>FUGA PISCINA</DESCRIPCION>
		<MATERIALES>
			<MATERIAL>ALB001</MATERIAL>
			<MATERIAL>FON002</MATERIAL>
		</MATERIALES>
		<ADMINISTRATIVO>88888888O</ADMINISTRATIVO>
		<OPERARIOS>
			<OPERARIO>55555555T</OPERARIO>
			<OPERARIO>99999999N</OPERARIO>
		</OPERARIOS>
		<INCIDENCIAS>
			<INCIDENCIA>
				<NUMERO>1</NUMERO>
				<DESCRIPCION>PISCINA LLENA</DESCRIPCION>
			</INCIDENCIA>
			<INCIDENCIA>
				<NUMERO>2</NUMERO>
				<DESCRIPCION>FALTA POLIESTER</DESCRIPCION>
			</INCIDENCIA>
		</INCIDENCIAS>
	</CITA>
	</CITAS>
</OBRICO>